cacao_accounting_desktop/__init__.py
cacao_accounting_desktop/__main.py
cacao_accounting_desktop/assets/CacaoAccounting.bmp
cacao_accounting_desktop/assets/CacaoAccounting.png
cacao_accounting_desktop/assets/CacaoAccountingRotate.bmp
cacao_accounting_desktop/assets/arrow-counterclockwise.png
cacao_accounting_desktop/assets/bmosoluciones.png
cacao_accounting_desktop/assets/play-fill.png
cacao_accounting_desktop/assets/plus-circle.png
cacao_accounting_desktop/assets/sliders.png
staging_cacao_accounting_desktop-2024.7.19.dist-info/LICENSE
staging_cacao_accounting_desktop-2024.7.19.dist-info/METADATA
staging_cacao_accounting_desktop-2024.7.19.dist-info/WHEEL
staging_cacao_accounting_desktop-2024.7.19.dist-info/entry_points.txt
staging_cacao_accounting_desktop-2024.7.19.dist-info/top_level.txt
staging_cacao_accounting_desktop-2024.7.19.dist-info/RECORD
